<?xml version="1.0" encoding="UTF-8"?>
<!DOCTYPE log4j:configuration SYSTEM "log4j.dtd">

<!-- $Id:-->

<!-- Current settings dictate that the core SCEC-VDO application and its
     plugins write to the same log file with plugins indented a few spaces;
     their respective log levels may be different though.
     
     All messages go to the console as well. Set the root logger level="off"
     to disable the console etc...-->
     
<log4j:configuration xmlns:log4j="http://jakarta.apache.org/log4j/">

    <!-- Log file appender -->
    <appender name="LOGFILE" class="org.apache.log4j.RollingFileAppender">
        <param name="File" value="logs/scec_vdo.log" />
        <param name="Append" value="true" />
        <param name="MaxFileSize" value="1MB" />
        <layout class="org.apache.log4j.PatternLayout">
            <param name="ConversionPattern" value="%-5p  (%F:%L) - %m%n"/>
        </layout>
    </appender>

    <!-- Console appender -->
    <appender name="CONSOLE" class="org.apache.log4j.ConsoleAppender">
        <layout class="org.apache.log4j.PatternLayout">
            <param name="ConversionPattern" value="%-5p  (%F:%L) - %m%n"/>
        </layout>
    </appender>

    <logger name="org.scec.geo3d">
        <level value="DEBUG" />
    </logger>
    
    <root>
        <level value="INFO" />
        <appender-ref ref="CONSOLE"/>
        <appender-ref ref="LOGFILE"/>
    </root>

</log4j:configuration>
